{
    "place_info": {
        "d_activity_gwj_section": "0-+",
        "d_brand_id_section": "0-+",
        "d_business_id": "",
        "d_business_type": "",
        "d_cater_book_pc_section": "0-+",
        "d_cater_book_wap_section": "0-+",
        "d_cater_rating_section": "0-+",
        "d_data_type": "",
        "d_discount2_section": "0-+",
        "d_discount_section": "0-+",
        "d_discount_tm2_section": "0-+",
        "d_discount_tm_section": "0-+",
        "d_dist": "0-+",
        "d_filt_type_section": "0-+",
        "d_free_section": "0-+",
        "d_groupon_section": "0-+",
        "d_groupon_type_section": "0-+",
        "d_health_score_section": "0-+",
        "d_hotel_attr_tags_section": "0-+",
        "d_hotel_book_pc_section": "0-+",
        "d_hotel_book_wap_section": "0-+",
        "d_hotel_detail_tag_section": "0-+",
        "d_hourly_day1_bookable_section": "0-+",
        "d_hourly_day1_fullroom_section": "0-+",
        "d_hourly_day1_price_section": "0-+",
        "d_hourly_day2_bookable_section": "0-+",
        "d_hourly_day2_fullroom_section": "0-+",
        "d_hourly_day2_price_section": "0-+",
        "d_hourly_day3_bookable_section": "0-+",
        "d_hourly_day3_fullroom_section": "0-+",
        "d_hourly_day3_price_section": "0-+",
        "d_hourly_day4_bookable_section": "0-+",
        "d_hourly_day4_fullroom_section": "0-+",
        "d_hourly_day4_price_section": "0-+",
        "d_hourly_day5_bookable_section": "0-+",
        "d_hourly_day5_fullroom_section": "0-+",
        "d_hourly_day5_price_section": "0-+",
        "d_level_section": "0-+",
        "d_lowprice_flag_section": "0-+",
        "d_meishipaihao_section": "0-+",
        "d_movie_book_section": "0-+",
        "d_overall_rating_section": "0-+",
        "d_parking_type_section": "0-+",
        "d_price_section": "0-+",
        "d_query_attr_type": "4",
        "d_rebate_section": "0-+",
        "d_room_section": "0-+",
        "d_sort_rule": "0",
        "d_sort_type": "",
        "d_spothot_section": "0-+",
        "d_sub_type": "",
        "d_support_imax_section": "0-+",
        "d_tag_filter": "0",
        "d_tag_info_list": "公司企业,广告公司",
        "d_tag_section": "0-+",
        "d_tags_beauty_section": "0-+",
        "d_tags_cater_section": "0-+",
        "d_tags_hospital_section": "0-+",
        "d_tags_hotel_section": "0-+",
        "d_tags_life_section": "0-+",
        "d_tags_scope_section": "0-+",
        "d_tags_shopping_section": "0-+",
        "d_ticket_book_flag_section": "0-+",
        "d_title_suffix_section": "0-+",
        "d_tonight_sale_flag_section": "0-+",
        "d_total_score_section": "0-+",
        "d_wise_price_section": "0-+",
        "search_ext": [{
            "title": "",
            "wd": "雨湖区广告"
        }]
    },
    "content": [{
        "acc_flag": 0,
        "addr": "湘潭市雨湖区韶山东路375号",
        "address_norm": "[湖南省(430000)|PROV|0|][湘潭市(430300)|CITY|1|][雨湖区(430302)|AREA|1|][韶山东路()|ROAD|1|375号$]",
        "admin_info": {
            "area_id": 430302,
            "area_name": "雨湖区",
            "city_id": 430300,
            "city_name": "湘潭市"
        },
        "aoi": "韶山东路;基建营",
        "api_admin_info": {
            "area_code": 8155,
            "area_name": "雨湖区",
            "city_code": 313,
            "city_name": "湘潭市",
            "prov_code": 26,
            "prov_name": "湖南省"
        },
        "area": 8155,
        "area_name": "湘潭市雨湖区",
        "biz_type": 0,
        "brand_id": null,
        "catalogID": 0,
        "cla": [],
        "click_flag": 0,
        "detail": 1,
        "diPointX": 1257039804,
        "diPointY": 321265380,
        "di_tag": "传媒公司 公司企业 广告公司",
        "dis": -1,
        "dist2route": 0,
        "dist2start": 0,
        "ext": {
            "detail_info": {
                "areaid": "8155",
                "content_sug": {
                    "search_ext_data": {
                        "full_text": []
                    },
                    "sug_ext_data": {
                        "full_text": [],
                        "sub_link_info": []
                    }
                },
                "display_info_comment_label": {
                    "hotel": "",
                    "life": ""
                },
                "display_info_redu": "0",
                "from_pds": "1",
                "image": "https://taojin-his.cdn.bcebos.com/500fd9f9d72a6059dd7086132e34349b033bba53.jpg",
                "link": [],
                "mbc": {
                    "markv": "3"
                },
                "name": "飞扬广告",
                "overall_rating": "",
                "phone": "",
                "poi_address": "湘潭市雨湖区韶山东路375号",
                "point": {
                    "x": 12570398.04,
                    "y": 3212653.8
                },
                "price": "",
                "shop_hours_flag": "",
                "std_tag": "公司企业;公司",
                "tag": "广告公司",
                "validate": 0,
                "vs_content": {
                    "invisible": {
                        "bigdata": {
                            "photo_album": [{
                                "icon_url": "https://map-mobile-lbsapp.cdn.bcebos.com/quanjing3x.png",
                                "jump_url": "baidumap://map/place/detail?popRoot=no&from=liebiao&uid=07211b05ed54675bf50e7732&show_type=detail_page&poi_ext_param={\"anchor\":{\"cardName\": \"phototab\", \"cardParams\": {\"currentTab\": \"panorama\"}}}",
                                "type": 1,
                                "url": "https://mapsv0.bdimg.com/?qt=pr3dpoi&uid=07211b05ed54675bf50e7732&width=1024&height=456&watermark=&fovy=60&quality=80"
                            }],
                            "showtag": "[[\"\\u5e7f\\u544a\\u516c\\u53f8\"], [\"\"], \"\", 0, \"\"]"
                        }
                    }
                }
            },
            "src_name": "enterprise"
        },
        "ext_display": {
            "display_info": {
                "catalog_fields": null,
                "impression_tag": {
                    "hotel": "",
                    "life": ""
                },
                "redu": "0",
                "source_map": [],
                "src_name": "display_info",
                "uids": ["5323051813344102186:redu"]
            }
        },
        "ext_type": 4,
        "f_flag": 2057,
        "father_son": 0,
        "geo": "1|12570398.04,3212653.80;12570398.04,3212653.80|12570398.04,3212653.80;",
        "geo_type": 2,
        "indoor_pano": "",
        "ismodified": 1,
        "name": "飞扬广告",
        "navi_update_time": 1586864658,
        "navi_x": "0",
        "navi_y": "0",
        "new_catalog_id": "140204",
        "pano": 1,
        "poiType": 0,
        "poi_click_num": 0,
        "poi_profile": 0,
        "primary_uid": "5323051813344102186",
        "prio_flag": 32,
        "profile_geo": "",
        "route_flag": 0,
        "show_tag": [],
        "status": 1,
        "std_tag": "公司企业;公司",
        "std_tag_id": "2502",
        "storage_src": "api",
        "street_id": "07211b05ed54675bf50e7732",
        "tag": "传媒公司 公司企业 <font color=\"#c60a00\">广告</font>公司",
        "ty": 2,
        "uid": "07211b05ed54675bf50e7732",
        "view_type": 0,
        "x": 1257039804,
        "y": 321265380
    }, {
        "acc_flag": 0,
        "addr": "湖南省湘潭市雨湖区宝庆路446-、448号",
        "address_norm": "[湖南省(430000)|PROV|1|][湘潭市(430300)|CITY|1|][雨湖区(430302)|AREA|1|][宝庆路()|ROAD|1|446-$]、448号",
        "admin_info": {
            "area_id": 430302,
            "area_name": "雨湖区",
            "city_id": 430300,
            "city_name": "湘潭市"
        },
        "aoi": "迎宾",
        "api_admin_info": {
            "area_code": 8155,
            "area_name": "雨湖区",
            "city_code": 313,
            "city_name": "湘潭市",
            "prov_code": 26,
            "prov_name": "湖南省"
        },
        "area": 8155,
        "area_name": "湘潭市雨湖区",
        "biz_type": 0,
        "brand_id": null,
        "catalogID": 0,
        "cla": [],
        "click_flag": 0,
        "detail": 1,
        "diPointX": 1256740805,
        "diPointY": 321119502,
        "di_tag": "传媒公司 公司企业 广告公司",
        "dis": -1,
        "dist2route": 0,
        "dist2start": 0,
        "ext": {
            "detail_info": {
                "areaid": "8155",
                "content_sug": {
                    "search_ext_data": {
                        "full_text": []
                    },
                    "sug_ext_data": {
                        "full_text": [],
                        "sub_link_info": []
                    }
                },
                "display_info_comment_label": {
                    "hotel": "",
                    "life": ""
                },
                "display_info_redu": "0",
                "from_pds": "1",
                "image": "https://taojin-his.cdn.bcebos.com/314e251f95cad1c8742c14b6763e6709c83d5188.jpg",
                "link": [],
                "mbc": {
                    "markv": "3"
                },
                "name": "浪文广告",
                "overall_rating": "",
                "phone": "(0731)52626808,13873278310",
                "phone_risk": {
                    "bid": "1889377789460022795",
                    "word": "如遇电话错误，可点击“报错”进行反馈"
                },
                "poi_address": "湖南省湘潭市雨湖区宝庆路446-、448号",
                "point": {
                    "x": 12567408.05,
                    "y": 3211195.02
                },
                "price": "",
                "shop_hours": "08:30-18:00",
                "shop_hours_flag": 1,
                "std_tag": "公司企业;公司",
                "tag": "广告公司",
                "validate": 0,
                "vs_content": {
                    "gray_line": {
                        "realtime_computation": {
                            "business_time": {
                                "data": [{
                                    "text": "08:30-18:00"
                                }],
                                "src_name": "mingdeng_bianji",
                                "text": "",
                                "tip": [],
                                "tpl_id": 1,
                                "tpl_name": "i"
                            }
                        },
                        "shophours": {
                            "business_time": {
                                "data": [{
                                    "text": "08:30-18:00"
                                }],
                                "src_name": "mingdeng_bianji",
                                "text": "",
                                "tip": [],
                                "tpl_id": 1,
                                "tpl_name": "i"
                            }
                        }
                    },
                    "invisible": {
                        "bigdata": {
                            "photo_album": [{
                                "icon_url": "https://map-mobile-lbsapp.cdn.bcebos.com/quanjing3x.png",
                                "jump_url": "baidumap://map/place/detail?popRoot=no&from=liebiao&uid=d029ed247ac0ef8f1188240d&show_type=detail_page&poi_ext_param={\"anchor\":{\"cardName\": \"phototab\", \"cardParams\": {\"currentTab\": \"panorama\"}}}",
                                "type": 1,
                                "url": "https://mapsv0.bdimg.com/?qt=pr3dpoi&uid=d029ed247ac0ef8f1188240d&width=1024&height=456&watermark=&fovy=60&quality=80"
                            }, {
                                "icon_url": "https://map-mobile-lbsapp.cdn.bcebos.com/tupian3x.png",
                                "jump_url": "baidumap://map/place/detail?popRoot=no&from=liebiao&uid=d029ed247ac0ef8f1188240d&show_type=detail_page&poi_ext_param={\"anchor\":{\"cardName\": \"phototab\", \"cardParams\": {\"currentTab\": \"photo\"}}}",
                                "type": 3,
                                "url": "https://timg01.bdimg.com/timg?pano&size=f720_540&quality=80&sec=0&di=586e7cdf10ff5971500d7f1006ed1edc&src=http%3A%2F%2Ftaojin-his.cdn.bcebos.com%2F314e251f95cad1c8742c14b6763e6709c83d5188.jpg"
                            }, {
                                "icon_url": "https://map-mobile-lbsapp.cdn.bcebos.com/tupian3x.png",
                                "jump_url": "baidumap://map/place/detail?popRoot=no&from=liebiao&uid=d029ed247ac0ef8f1188240d&show_type=detail_page&poi_ext_param={\"anchor\":{\"cardName\": \"phototab\", \"cardParams\": {\"currentTab\": \"photo\"}}}",
                                "type": 3,
                                "url": "https://timg01.bdimg.com/timg?pano&size=f720_540&quality=80&sec=0&di=702c8b66bc6a01d78d71c4f3fef77d0e&src=http%3A%2F%2Ftaojin-his.cdn.bcebos.com%2F71cf3bc79f3df8dc124f4c00c411728b47102835.jpg"
                            }, {
                                "icon_url": "https://map-mobile-lbsapp.cdn.bcebos.com/tupian3x.png",
                                "jump_url": "baidumap://map/place/detail?popRoot=no&from=liebiao&uid=d029ed247ac0ef8f1188240d&show_type=detail_page&poi_ext_param={\"anchor\":{\"cardName\": \"phototab\", \"cardParams\": {\"currentTab\": \"photo\"}}}",
                                "type": 3,
                                "url": "https://timg01.bdimg.com/timg?pano&size=f720_540&quality=80&sec=0&di=2a4b1b007b98bb6adebcd014418c5277&src=http%3A%2F%2Ftaojin-his.cdn.bcebos.com%2F4bed2e738bd4b31ca10c40108cd6277f9e2ff86d.jpg"
                            }],
                            "showtag": "[[\"\\u5e7f\\u544a\\u516c\\u53f8\"], [\"\"], \"\", 0, \"\"]"
                        }
                    }
                }
            },
            "src_name": "enterprise"
        },
        "ext_display": {
            "display_info": {
                "catalog_fields": null,
                "impression_tag": {
                    "hotel": "",
                    "life": ""
                },
                "redu": "0",
                "source_map": {
                    "shop_hours": {
                        "field_name": "webmining",
                        "priority": "0",
                        "uid": "1889377789460022795:webmining",
                        "update_time": "1549790392.0131"
                    }
                },
                "src_name": "display_info",
                "uids": ["1889377789460022795:redu", "1889377789460022795:webmining"]
            }
        },
        "ext_type": 4,
        "f_flag": 2057,
        "father_son": 0,
        "geo": "1|12567408.05,3211195.02;12567408.05,3211195.02|12567408.05,3211195.02;",
        "geo_type": 2,
        "indoor_pano": "",
        "ismodified": 0,
        "name": "浪文广告",
        "navi_update_time": 1591046697,
        "navi_x": "0",
        "navi_y": "0",
        "new_catalog_id": "140204",
        "pano": 1,
        "poiType": 0,
        "poi_click_num": 0,
        "poi_profile": 0,
        "primary_uid": "1889377789460022795",
        "prio_flag": 32,
        "route_flag": 0,
        "show_tag": [],
        "status": 1,
        "std_tag": "公司企业;公司",
        "std_tag_id": "2502",
        "storage_src": "api",
        "street_id": "d029ed247ac0ef8f1188240d",
        "tag": "传媒公司 公司企业 <font color=\"#c60a00\">广告</font>公司",
        "tel": "(0731)52626808,13873278310",
        "ty": 2,
        "uid": "d029ed247ac0ef8f1188240d",
        "view_type": 0,
        "x": 1256740805,
        "y": 321119502
    }, {
        "acc_flag": 0,
        "addr": "湖南省湘潭市雨湖区韶山东路458附近",
        "address_norm": "[湖南省(430000)|PROV|1|][湘潭市(430300)|CITY|1|][雨湖区(430302)|AREA|1|][韶山东路()|ROAD|1|458$]附近",
        "admin_info": {
            "area_id": 430302,
            "area_name": "雨湖区",
            "city_id": 430300,
            "city_name": "湘潭市"
        },
        "aoi": "韶山东路",
        "api_admin_info": {
            "area_code": 8155,
            "area_name": "雨湖区",
            "city_code": 313,
            "city_name": "湘潭市",
            "prov_code": 26,
            "prov_name": "湖南省"
        },
        "area": 8155,
        "area_name": "湘潭市雨湖区",
        "biz_type": 0,
        "brand_id": null,
        "catalogID": 0,
        "cla": [],
        "click_flag": 0,
        "detail": 1,
        "diPointX": 1257053299,
        "diPointY": 321278336,
        "di_tag": "图文快印 生活服务 公司企业 广告公司",
        "dis": -1,
        "dist2route": 0,
        "dist2start": 0,
        "ext": {
            "detail_info": {
                "areaid": "8155",
                "content_sug": {
                    "search_ext_data": {
                        "full_text": []
                    },
                    "sug_ext_data": {
                        "full_text": [],
                        "sub_link_info": []
                    }
                },
                "display_info_comment_label": {
                    "hotel": "",
                    "life": ""
                },
                "display_info_redu": "0",
                "from_pds": "1",
                "image": "https://taojin-his.cdn.bcebos.com/86d6277f9e2f0708464d839ae724b899a801f2e4.jpg",
                "link": [],
                "mbc": {
                    "markv": "3"
                },
                "name": "星诚图文广告",
                "overall_rating": "",
                "phone": "",
                "poi_address": "湖南省湘潭市雨湖区韶山东路458附近",
                "point": {
                    "x": 12570532.99,
                    "y": 3212783.36
                },
                "price": "",
                "shop_hours_flag": "",
                "std_tag": "公司企业;公司",
                "tag": "广告公司",
                "validate": 0,
                "vs_content": {
                    "invisible": {
                        "bigdata": {
                            "showtag": "[[\"\\u5e7f\\u544a\\u516c\\u53f8\"], [\"\"], \"\", 0, \"\"]"
                        }
                    }
                }
            },
            "src_name": "enterprise"
        },
        "ext_display": {
            "display_info": {
                "catalog_fields": null,
                "impression_tag": {
                    "hotel": "",
                    "life": ""
                },
                "redu": "0",
                "source_map": [],
                "src_name": "display_info",
                "uids": ["9150696788114890631:redu"]
            }
        },
        "ext_type": 4,
        "f_flag": 2057,
        "father_son": 0,
        "geo": "1|12570532.99,3212783.36;12570532.99,3212783.36|12570532.99,3212783.36;",
        "geo_type": 2,
        "name": "星诚图文广告",
        "navi_update_time": 1591951843,
        "navi_x": "0",
        "navi_y": "0",
        "new_catalog_id": "140204",
        "poiType": 0,
        "poi_click_num": 0,
        "poi_profile": 0,
        "primary_uid": "9150696788114890631",
        "prio_flag": 32,
        "route_flag": 0,
        "show_tag": [],
        "status": 1,
        "std_tag": "公司企业;公司",
        "std_tag_id": "2502",
        "storage_src": "api",
        "tag": "图文快印 生活服务 公司企业 <font color=\"#c60a00\">广告</font>公司",
        "ty": 2,
        "uid": "a75d79ed407de73738221cae",
        "view_type": 0,
        "x": 1257053299,
        "y": 321278336
    }, {
        "acc_flag": 0,
        "addr": "韶山西路143号芙蓉电影院对面",
        "address_norm": "[湖南省(430000)|PROV|0|][湘潭市(430300)|CITY|0|][雨湖区(430302)|AREA|0|][韶山西路()|ROAD|1|]143号芙蓉电影院对面",
        "admin_info": {
            "area_id": 430302,
            "area_name": "雨湖区",
            "city_id": 430300,
            "city_name": "湘潭市"
        },
        "alias": ["创兴图文广告(韶山西路)"],
        "aoi": "解放南路;韶山西路",
        "api_admin_info": {
            "area_code": 8155,
            "area_name": "雨湖区",
            "city_code": 313,
            "city_name": "湘潭市",
            "prov_code": 26,
            "prov_name": "湖南省"
        },
        "area": 8155,
        "area_name": "湘潭市雨湖区",
        "biz_type": 0,
        "brand_id": null,
        "catalogID": 124,
        "cla": [
            [15, "购物"],
            [124, "文化办公"]
        ],
        "click_flag": 0,
        "detail": 1,
        "diPointX": 1256887300,
        "diPointY": 321216400,
        "di_tag": "图文快印 打印复印 生活服务 广告图文",
        "dis": -1,
        "dist2route": 0,
        "dist2start": 0,
        "ext": {
            "detail_info": {
                "areaid": "8155",
                "bangdan": [{
                    "bd_score": 8.9,
                    "bd_url": "https://newclient.map.baidu.com/client/cube/feed/newhotlistpage/?versionManage=new&pass_back=d2695e509ba514664c910fcf7e57edd3",
                    "name": "313-生活服务-area-雨湖区-renqi-雨湖区最佳人气图文快印排行榜",
                    "yiji_t1": {
                        "l1": "雨湖区最佳人气图文快印排行榜",
                        "l1_tag": 1
                    }
                }],
                "comment_num": 2,
                "comments": [{
                    "cn_name": "百度地图",
                    "comment_jump_url": "https://ugc.map.baidu.com/cube/comment/choicepage?comment_sort=1&tab=1&uid=97c8d72544fe41f4a0acc4f1",
                    "comment_photo": [{
                        "pic_name": null,
                        "pic_url": "https://lbsugc.cdn.bcebos.com/images/H267f9e2f070828382c790bb0bc99a9014c08f11a.jpg"
                    }],
                    "content": "",
                    "date": "2015-03-23 23:40",
                    "one_url_mobile": null,
                    "overall_rating": 0,
                    "user_logo": null,
                    "user_name": "丫丫一根葱"
                }, {
                    "cn_name": "百度地图",
                    "comment_jump_url": "https://ugc.map.baidu.com/cube/comment/choicepage?comment_sort=1&tab=1&uid=97c8d72544fe41f4a0acc4f1",
                    "comment_photo": [{
                        "pic_name": null,
                        "pic_url": "https://lbsugc.cdn.bcebos.com/images/H9f510fb30f2442a79726505fd343ad4bd113021b.jpg"
                    }],
                    "content": "",
                    "date": "2014-05-28 18:28",
                    "one_url_mobile": null,
                    "overall_rating": 0,
                    "user_logo": null,
                    "user_name": "面吃多了要吐"
                }],
                "content_sug": {
                    "search_ext_data": {
                        "full_text": [{
                            "content": [
                                ["查看图片"],
                                ["#333333"]
                            ],
                            "jump_info": "baidumap://map/place/detail?popRoot=no&from=liebiao&show_type=detail_page&poi_ext_param=%7b%22anchor%22%3a%7b%22cardName%22%3a%22phototab%22%2c%22cardParams%22%3a%7b%22currentTab%22%3a%22photo%22%7d%7d%7d&uid=97c8d72544fe41f4a0acc4f1",
                            "label": [
                                ["图片"],
                                ["#F76545"], "#F76545", 4
                            ],
                            "priority": 6,
                            "type": 9
                        }]
                    },
                    "sug_ext_data": {
                        "full_text": [],
                        "sub_link_info": [{
                            "condition": [
                                [], 0, 0, 0, [0],
                                [0, 1],
                                ["", ""],
                                [0, 0]
                            ],
                            "content": [
                                ["查看图片"],
                                ["#333333"], 0, 0, 0, "", ""
                            ],
                            "jump_info": ["jumpto", "baidumap://map/place/detail?popRoot=no&from=liebiao&show_type=detail_page&poi_ext_param=%7b%22anchor%22%3a%7b%22cardName%22%3a%22phototab%22%2c%22cardParams%22%3a%7b%22currentTab%22%3a%22photo%22%7d%7d%7d&uid=97c8d72544fe41f4a0acc4f1"],
                            "label": [
                                ["图片"],
                                ["#F76545"], 0, 1, 4, "#F76545", ""
                            ],
                            "priority": 6,
                            "space": 2,
                            "type": 9
                        }]
                    }
                },
                "display_info_comment_label": {
                    "hotel": "",
                    "life": ""
                },
                "display_info_redu": "68",
                "from_pds": "1",
                "image": "https://taojin-his.cdn.bcebos.com/b03533fa828ba61edcded2954f34970a304e5953.jpg",
                "image_num": 7,
                "link": [],
                "mbc": {
                    "markv": "3"
                },
                "name": "创兴图文(韶山西路店)",
                "overall_rating": "0.0",
                "owner_id": "",
                "phone": "18707325391",
                "phone_risk": {
                    "bid": "13510545905220514511",
                    "word": "如遇电话错误，可点击“报错”进行反馈"
                },
                "poi_address": "韶山西路143号芙蓉电影院对面",
                "point": {
                    "x": 12568873,
                    "y": 3212164
                },
                "rec_reason": "",
                "shop_hours": "08:30-21:00",
                "shop_hours_flag": 1,
                "status_label": "",
                "std_tag": "生活服务;图文快印店",
                "tag": "图文快印",
                "validate": 0,
                "vs_content": {
                    "gray_line": {
                        "realtime_computation": {
                            "business_time": {
                                "data": [{
                                    "text": "08:30-21:00"
                                }],
                                "src_name": "normal",
                                "text": "",
                                "tip": [],
                                "tpl_id": 1,
                                "tpl_name": "i"
                            }
                        },
                        "shophours": {
                            "business_time": {
                                "data": [{
                                    "text": "08:30-21:00"
                                }],
                                "src_name": "normal",
                                "text": "",
                                "tip": [],
                                "tpl_id": 1,
                                "tpl_name": "i"
                            }
                        }
                    },
                    "invisible": {
                        "bigdata": {
                            "dyn_style": "{\"dish\": [[\"\\u63a8\\u8350\\u83dc:{name}\", \"\"], [\"24\", \"24\"], \"310\", 2, \"\"]}",
                            "idx_type": "{\"1\": \"\\u83dc\\u54c1\", \"2\": \"\\u670d\\u52a1\\u5185\\u5bb9\", \"3\": \"\\u5546\\u54c1\", \"4\": \"\\u5b50\\u7c7b\\u578b\"}",
                            "photo_album": [{
                                "detail_url": "baidumap://map/component?target=street_scape_page&comName=streetscape&popRoot=no&param=%7B%22uid%22%3A%2297c8d72544fe41f4a0acc4f1%22%2C%22panotype%22%3A%22street%22%2C%22from_source%22%3A%22poidetail%22%7D",
                                "icon_url": "https://map-mobile-lbsapp.cdn.bcebos.com/quanjing3x.png",
                                "jump_url": "baidumap://map/place/detail?popRoot=no&from=liebiao&uid=97c8d72544fe41f4a0acc4f1&show_type=detail_page&poi_ext_param={\"anchor\":{\"cardName\": \"phototab\", \"cardParams\": {\"currentTab\": \"panorama\"}}}",
                                "type": 1,
                                "url": "https://mapsv0.bdimg.com/?qt=pr3dpoi&uid=97c8d72544fe41f4a0acc4f1&width=1024&height=456&watermark=&fovy=60&quality=80"
                            }, {
                                "icon_url": "https://map-mobile-lbsapp.cdn.bcebos.com/tupian3x.png",
                                "jump_url": "baidumap://map/place/detail?popRoot=no&from=liebiao&uid=97c8d72544fe41f4a0acc4f1&show_type=detail_page&poi_ext_param={\"anchor\":{\"cardName\": \"phototab\", \"cardParams\": {\"currentTab\": \"photo\"}}}",
                                "type": 3,
                                "url": "https://timg01.bdimg.com/timg?pano&size=f720_540&quality=80&sec=0&di=88af64689f71b509af5b45c244324119&src=http%3A%2F%2Ftaojin-his.cdn.bcebos.com%2Fb03533fa828ba61edcded2954f34970a304e5953.jpg"
                            }, {
                                "icon_url": "https://map-mobile-lbsapp.cdn.bcebos.com/tupian3x.png",
                                "jump_url": "baidumap://map/place/detail?popRoot=no&from=liebiao&uid=97c8d72544fe41f4a0acc4f1&show_type=detail_page&poi_ext_param={\"anchor\":{\"cardName\": \"phototab\", \"cardParams\": {\"currentTab\": \"photo\"}}}",
                                "type": 3,
                                "url": "https://timg01.bdimg.com/timg?pano&size=f720_540&quality=80&sec=0&di=cc30dbffa4b16869e428fc4382199099&src=http%3A%2F%2Ftaojin-pic-gz.cdn.bcebos.com%2Fbos_gz_bbcb24c9e75898c5880c055cdfdddafd.jpg"
                            }, {
                                "icon_url": "https://map-mobile-lbsapp.cdn.bcebos.com/tupian3x.png",
                                "jump_url": "baidumap://map/place/detail?popRoot=no&from=liebiao&uid=97c8d72544fe41f4a0acc4f1&show_type=detail_page&poi_ext_param={\"anchor\":{\"cardName\": \"phototab\", \"cardParams\": {\"currentTab\": \"photo\"}}}",
                                "type": 3,
                                "url": "https://timg01.bdimg.com/timg?pano&size=f720_540&quality=80&sec=0&di=e90273b2c876e98512496faf99e5b6d1&src=http%3A%2F%2Ftaojin-his.cdn.bcebos.com%2F7e3e6709c93d70cf4170a909f7dcd100baa12b2f.jpg"
                            }],
                            "showtag": "[[\"\\u56fe\\u6587\\u5feb\\u5370\"], [\"\"], \"\", 0, \"\"]",
                            "style": "{\"24\": \"#F76454\", \"310\": \"#FEEFED\"}",
                            "tags1": "[[[\"WiFi\"], [\"\"], \"\", 1, \"\"], [[\"68\\u4eba\\u8bbf\\u95ee\"], [\"\"], \"\", 1, \"\"]]"
                        }
                    }
                }
            },
            "src_name": "life"
        },
        "ext_display": {
            "display_info": {
                "catalog_fields": null,
                "impression_tag": {
                    "hotel": "",
                    "life": ""
                },
                "redu": "68",
                "source_map": [],
                "src_name": "display_info",
                "uids": ["13510545905220514511:redu"]
            }
        },
        "ext_type": 4,
        "f_flag": 24,
        "father_son": 0,
        "geo": "1|12568873.00,3212164.00;12568873.00,3212164.00|12568873.00,3212164.00;",
        "geo_type": 2,
        "indoor_pano": "",
        "ismodified": 1,
        "name": "创兴图文(韶山西路店)",
        "navi_update_time": 1592069435,
        "navi_x": "0",
        "navi_y": "0",
        "new_catalog_id": "050501",
        "pano": 1,
        "poiType": 0,
        "poi_click_num": 0,
        "poi_profile": 0,
        "primary_uid": "13510545905220514511",
        "prio_flag": 32,
        "route_flag": 0,
        "show_tag": [],
        "status": 1,
        "std_tag": "生活服务;图文快印店",
        "std_tag_id": "1307",
        "storage_src": "api",
        "street_id": "97c8d72544fe41f4a0acc4f1",
        "tag": "图文快印 打印复印 生活服务 <font color=\"#c60a00\">广告</font>图文",
        "tel": "18707325391",
        "ty": 2,
        "uid": "97c8d72544fe41f4a0acc4f1",
        "view_type": 0,
        "x": 1256887300,
        "y": 321216400
    }, {
        "acc_flag": 0,
        "addr": "湘潭市雨湖区幸福楼3栋附1号",
        "address_norm": "[湖南省(430000)|PROV|0|][湘潭市(430300)|CITY|1|][雨湖区(430302)|AREA|1|][白马湖路()|ROAD|0|]幸福楼3栋附1号",
        "admin_info": {
            "area_id": 430302,
            "area_name": "雨湖区",
            "city_id": 430300,
            "city_name": "湘潭市"
        },
        "alias": ["湘潭市雨湖区科弈广告经营部"],
        "aoi": "中山路;白石广场",
        "api_admin_info": {
            "area_code": 8155,
            "area_name": "雨湖区",
            "city_code": 313,
            "city_name": "湘潭市",
            "prov_code": 26,
            "prov_name": "湖南省"
        },
        "area": 8155,
        "area_name": "湘潭市雨湖区",
        "biz_type": 0,
        "brand_id": null,
        "catalogID": 0,
        "cla": [],
        "click_flag": 0,
        "detail": 1,
        "diPointX": 1256897103,
        "diPointY": 321111898,
        "di_tag": "传媒公司 公司企业 广告公司",
        "dis": -1,
        "dist2route": 0,
        "dist2start": 0,
        "ext": {
            "detail_info": {
                "areaid": "8155",
                "content_sug": {
                    "search_ext_data": {
                        "full_text": []
                    },
                    "sug_ext_data": {
                        "full_text": [],
                        "sub_link_info": []
                    }
                },
                "display_info_comment_label": {
                    "hotel": "",
                    "life": ""
                },
                "display_info_redu": "0",
                "from_pds": "1",
                "image": "https://taojin-his.cdn.bcebos.com/caef76094b36acafb32a75df7fd98d1000e99ccf.jpg",
                "link": [],
                "mbc": {
                    "markv": "3"
                },
                "name": "科弈广告",
                "navi_xy": {
                    "bid": "14801745924577749533",
                    "diPoint": {
                        "x": 12568972.87,
                        "y": 3211123.76
                    },
                    "navi_info": [{
                        "bid": 0,
                        "from": "",
                        "is_traffic": 1,
                        "name": "",
                        "navi_x": "12568985.5152",
                        "navi_y": "3211130.9261",
                        "reserve": "",
                        "uid": "2bfcb14cf5cb2cfcc23644f2"
                    }]
                },
                "overall_rating": "",
                "phone": "",
                "poi_address": "湘潭市雨湖区幸福楼3栋附1号",
                "point": {
                    "x": 12568971.03,
                    "y": 3211118.98
                },
                "price": "",
                "shop_hours": "09:00-18:30",
                "shop_hours_flag": 1,
                "std_tag": "公司企业;公司",
                "tag": "广告公司",
                "validate": 0,
                "vs_content": {
                    "gray_line": {
                        "realtime_computation": {
                            "business_time": {
                                "data": [{
                                    "text": "09:00-18:30"
                                }],
                                "src_name": "mingdeng_bianji",
                                "text": "",
                                "tip": [],
                                "tpl_id": 1,
                                "tpl_name": "i"
                            }
                        },
                        "shophours": {
                            "business_time": {
                                "data": [{
                                    "text": "09:00-18:30"
                                }],
                                "src_name": "mingdeng_bianji",
                                "text": "",
                                "tip": [],
                                "tpl_id": 1,
                                "tpl_name": "i"
                            }
                        }
                    },
                    "invisible": {
                        "bigdata": {
                            "photo_album": [{
                                "detail_url": "baidumap://map/component?target=street_scape_page&comName=streetscape&popRoot=no&param=%7B%22uid%22%3A%22eae966f2cc5984c49b68b49a%22%2C%22panotype%22%3A%22street%22%2C%22from_source%22%3A%22poidetail%22%7D",
                                "icon_url": "https://map-mobile-lbsapp.cdn.bcebos.com/quanjing3x.png",
                                "jump_url": "baidumap://map/place/detail?popRoot=no&from=liebiao&uid=eae966f2cc5984c49b68b49a&show_type=detail_page&poi_ext_param={\"anchor\":{\"cardName\": \"phototab\", \"cardParams\": {\"currentTab\": \"panorama\"}}}",
                                "type": 1,
                                "url": "https://mapsv0.bdimg.com/?qt=pr3dpoi&uid=eae966f2cc5984c49b68b49a&width=1024&height=456&watermark=&fovy=60&quality=80"
                            }],
                            "showtag": "[[\"\\u5e7f\\u544a\\u516c\\u53f8\"], [\"\"], \"\", 0, \"\"]"
                        }
                    }
                }
            },
            "src_name": "enterprise"
        },
        "ext_display": {
            "display_info": {
                "catalog_fields": null,
                "impression_tag": {
                    "hotel": "",
                    "life": ""
                },
                "redu": "0",
                "source_map": {
                    "shop_hours": {
                        "field_name": "webmining",
                        "priority": "0",
                        "uid": "14801745924577749533:webmining",
                        "update_time": "1549799104.9962"
                    }
                },
                "src_name": "display_info",
                "uids": ["14801745924577749533:proc", "14801745924577749533:redu", "14801745924577749533:webmining"]
            }
        },
        "ext_type": 4,
        "f_flag": 2331,
        "father_son": 0,
        "geo": "1|12568971.03,3211118.98;12568971.03,3211118.98|12568971.03,3211118.98;",
        "geo_type": 2,
        "indoor_pano": "",
        "ismodified": 1,
        "name": "科弈广告",
        "navi_update_time": 1591049750,
        "navi_x": "12568985.5152",
        "navi_y": "3211130.9261",
        "new_catalog_id": "140204",
        "pano": 1,
        "poiType": 0,
        "poi_click_num": 0,
        "poi_profile": 0,
        "primary_uid": "14801745924577749533",
        "prio_flag": 32,
        "route_flag": 0,
        "show_tag": [],
        "status": 1,
        "std_tag": "公司企业;公司",
        "std_tag_id": "2502",
        "storage_src": "api",
        "street_id": "eae966f2cc5984c49b68b49a",
        "tag": "传媒公司 公司企业 <font color=\"#c60a00\">广告</font>公司",
        "ty": 2,
        "uid": "eae966f2cc5984c49b68b49a",
        "view_type": 0,
        "x": 1256897103,
        "y": 321111898
    }, {
        "acc_flag": 0,
        "addr": "湘潭市雨湖区宝庆路与金宝巷交叉路口往西南约100米(湘潭建筑装饰材料市场)",
        "address_norm": "[湖南省(430000)|PROV|0|][湘潭市(430300)|CITY|1|][雨湖区(430302)|AREA|1|][宝庆路()|ROAD|1|]与金宝巷交叉路口往西南约100米(湘潭建筑装饰材料市场)",
        "admin_info": {
            "area_id": 430302,
            "area_name": "雨湖区",
            "city_id": 430300,
            "city_name": "湘潭市"
        },
        "aoi": "迎宾",
        "api_admin_info": {
            "area_code": 8155,
            "area_name": "雨湖区",
            "city_code": 313,
            "city_name": "湘潭市",
            "prov_code": 26,
            "prov_name": "湖南省"
        },
        "area": 8155,
        "area_name": "湘潭市雨湖区",
        "biz_type": 0,
        "brand_id": null,
        "catalogID": 0,
        "cla": [],
        "click_flag": 0,
        "detail": 1,
        "diPointX": 1256698600,
        "diPointY": 321129100,
        "di_tag": "文化传媒 广告公司 公司企业",
        "dis": -1,
        "dist2route": 0,
        "dist2start": 0,
        "ext": {
            "detail_info": {
                "areaid": "8155",
                "content_sug": {
                    "search_ext_data": {
                        "full_text": []
                    },
                    "sug_ext_data": {
                        "full_text": [],
                        "sub_link_info": []
                    }
                },
                "from_pds": "1",
                "image": "https://taojin-pic-gz.cdn.bcebos.com/bos_gz_673c8f67914239f19018b829fa02511d.jpg",
                "link": [],
                "mbc": {
                    "markv": "3"
                },
                "name": "湘潭市雨湖区福宝广告服务部",
                "overall_rating": "",
                "phone": "",
                "poi_address": "湘潭市雨湖区宝庆路与金宝巷交叉路口往西南约100米(湘潭建筑装饰材料市场)",
                "point": {
                    "x": 12566986,
                    "y": 3211291
                },
                "price": "",
                "shop_hours_flag": "",
                "std_tag": "公司企业;公司",
                "tag": "公司",
                "validate": 0,
                "vs_content": {
                    "invisible": {
                        "bigdata": {
                            "photo_album": [{
                                "icon_url": "https://map-mobile-lbsapp.cdn.bcebos.com/tupian3x.png",
                                "jump_url": "baidumap://map/place/detail?popRoot=no&from=liebiao&uid=664abb4d7fb4a0771d1d1152&show_type=detail_page&poi_ext_param={\"anchor\":{\"cardName\": \"phototab\", \"cardParams\": {\"currentTab\": \"photo\"}}}",
                                "type": 3,
                                "url": "https://timg01.bdimg.com/timg?pano&size=f720_540&quality=80&sec=0&di=4b17c7080d93f2ae23e20eb89dd45deb&src=http%3A%2F%2Ftaojin-pic-gz.cdn.bcebos.com%2Fbos_gz_673c8f67914239f19018b829fa02511d.jpg"
                            }, {
                                "icon_url": "https://map-mobile-lbsapp.cdn.bcebos.com/tupian3x.png",
                                "jump_url": "baidumap://map/place/detail?popRoot=no&from=liebiao&uid=664abb4d7fb4a0771d1d1152&show_type=detail_page&poi_ext_param={\"anchor\":{\"cardName\": \"phototab\", \"cardParams\": {\"currentTab\": \"photo\"}}}",
                                "type": 3,
                                "url": "https://timg01.bdimg.com/timg?pano&size=f720_540&quality=80&sec=0&di=c5312d8691ba4196eeb8e3a566e3793a&src=http%3A%2F%2Ftaojin-his.cdn.bcebos.com%2F50da81cb39dbb6fd54d316220624ab18972b372d.jpg"
                            }],
                            "showtag": "[[\"\\u516c\\u53f8\"], [\"\"], \"\", 0, \"\"]"
                        }
                    }
                }
            },
            "src_name": "enterprise"
        },
        "ext_display": null,
        "ext_type": 4,
        "f_flag": 267,
        "father_son": 0,
        "geo": "1|12566986.00,3211291.00;12566986.00,3211291.00|12566986.00,3211291.00;",
        "geo_type": 2,
        "name": "湘潭市雨湖区福宝广告服务部",
        "navi_update_time": 1593914098,
        "navi_x": "0",
        "navi_y": "0",
        "new_catalog_id": "140204",
        "poiType": 0,
        "poi_click_num": 0,
        "poi_profile": 0,
        "primary_uid": "800581482871415726",
        "prio_flag": 32,
        "route_flag": 0,
        "show_tag": [],
        "status": 1,
        "std_tag": "公司企业;公司",
        "std_tag_id": "2502",
        "storage_src": "api",
        "tag": "文化传媒 <font color=\"#c60a00\">广告</font>公司 公司企业",
        "ty": 2,
        "uid": "664abb4d7fb4a0771d1d1152",
        "view_type": 0,
        "x": 1256698600,
        "y": 321129100
    }, {
        "acc_flag": 0,
        "addr": "湘潭市雨湖区韶山东路377号",
        "address_norm": "[湖南省(430000)|PROV|0|][湘潭市(430300)|CITY|1|][雨湖区(430302)|AREA|1|][韶山东路()|ROAD|1|377号$]",
        "admin_info": {
            "area_id": 430302,
            "area_name": "雨湖区",
            "city_id": 430300,
            "city_name": "湘潭市"
        },
        "alias": ["钰娇广告图文"],
        "aoi": "韶山东路",
        "api_admin_info": {
            "area_code": 8155,
            "area_name": "雨湖区",
            "city_code": 313,
            "city_name": "湘潭市",
            "prov_code": 26,
            "prov_name": "湖南省"
        },
        "area": 8155,
        "area_name": "湘潭市雨湖区",
        "biz_type": 0,
        "brand_id": null,
        "catalogID": 16,
        "cla": [
            [16, "生活服务"]
        ],
        "click_flag": 0,
        "detail": 1,
        "diPointX": 1257086378,
        "diPointY": 321292862,
        "di_tag": "文化传媒 广告公司 公司企业",
        "dis": -1,
        "dist2route": 0,
        "dist2start": 0,
        "ext": {
            "detail_info": {
                "areaid": "8155",
                "content_sug": {
                    "search_ext_data": {
                        "full_text": []
                    },
                    "sug_ext_data": {
                        "full_text": [],
                        "sub_link_info": []
                    }
                },
                "display_info_comment_label": {
                    "hotel": "",
                    "life": ""
                },
                "display_info_redu": "0",
                "from_pds": "1",
                "image": "https://taojin-his.cdn.bcebos.com/d058ccbf6c81800aef3b1b94bf3533fa838b474a.jpg",
                "link": [],
                "mbc": {
                    "markv": "3"
                },
                "name": "钰姣广告",
                "navi_xy": {
                    "bid": "2103382395956613259",
                    "diPoint": {
                        "x": 12570852.76,
                        "y": 3212924.3
                    },
                    "navi_info": []
                },
                "overall_rating": "0.0",
                "phone": "",
                "poi_address": "湘潭市雨湖区韶山东路377号",
                "point": {
                    "x": 12570863.78,
                    "y": 3212928.62
                },
                "price": "",
                "shop_hours": "09:00-18:30",
                "shop_hours_flag": 1,
                "std_tag": "公司企业;公司",
                "tag": "广告公司",
                "validate": 0,
                "vs_content": {
                    "gray_line": {
                        "realtime_computation": {
                            "business_time": {
                                "data": [{
                                    "text": "09:00-18:30"
                                }],
                                "src_name": "mingdeng_bianji",
                                "text": "",
                                "tip": [],
                                "tpl_id": 1,
                                "tpl_name": "i"
                            }
                        },
                        "shophours": {
                            "business_time": {
                                "data": [{
                                    "text": "09:00-18:30"
                                }],
                                "src_name": "mingdeng_bianji",
                                "text": "",
                                "tip": [],
                                "tpl_id": 1,
                                "tpl_name": "i"
                            }
                        }
                    },
                    "invisible": {
                        "bigdata": {
                            "photo_album": [{
                                "detail_url": "baidumap://map/component?target=street_scape_page&comName=streetscape&popRoot=no&param=%7B%22uid%22%3A%22b8277b46313bb375940319ad%22%2C%22panotype%22%3A%22street%22%2C%22from_source%22%3A%22poidetail%22%7D",
                                "icon_url": "https://map-mobile-lbsapp.cdn.bcebos.com/quanjing3x.png",
                                "jump_url": "baidumap://map/place/detail?popRoot=no&from=liebiao&uid=b8277b46313bb375940319ad&show_type=detail_page&poi_ext_param={\"anchor\":{\"cardName\": \"phototab\", \"cardParams\": {\"currentTab\": \"panorama\"}}}",
                                "type": 1,
                                "url": "https://mapsv0.bdimg.com/?qt=pr3dpoi&uid=b8277b46313bb375940319ad&width=1024&height=456&watermark=&fovy=60&quality=80"
                            }, {
                                "icon_url": "https://map-mobile-lbsapp.cdn.bcebos.com/tupian3x.png",
                                "jump_url": "baidumap://map/place/detail?popRoot=no&from=liebiao&uid=b8277b46313bb375940319ad&show_type=detail_page&poi_ext_param={\"anchor\":{\"cardName\": \"phototab\", \"cardParams\": {\"currentTab\": \"photo\"}}}",
                                "type": 3,
                                "url": "https://timg01.bdimg.com/timg?pano&size=f720_540&quality=80&sec=0&di=e63da4996c39a697d509c77a4514767e&src=http%3A%2F%2Ftaojin-his.cdn.bcebos.com%2Fd058ccbf6c81800aef3b1b94bf3533fa838b474a.jpg"
                            }, {
                                "icon_url": "https://map-mobile-lbsapp.cdn.bcebos.com/tupian3x.png",
                                "jump_url": "baidumap://map/place/detail?popRoot=no&from=liebiao&uid=b8277b46313bb375940319ad&show_type=detail_page&poi_ext_param={\"anchor\":{\"cardName\": \"phototab\", \"cardParams\": {\"currentTab\": \"photo\"}}}",
                                "type": 3,
                                "url": "https://timg01.bdimg.com/timg?pano&size=f720_540&quality=80&sec=0&di=f3f10cb894909e182ba1b0fbb4c6b440&src=http%3A%2F%2Ftaojin-his.cdn.bcebos.com%2F622762d0f703918fd8c4a0505f3d269759eec417.jpg"
                            }, {
                                "icon_url": "https://map-mobile-lbsapp.cdn.bcebos.com/tupian3x.png",
                                "jump_url": "baidumap://map/place/detail?popRoot=no&from=liebiao&uid=b8277b46313bb375940319ad&show_type=detail_page&poi_ext_param={\"anchor\":{\"cardName\": \"phototab\", \"cardParams\": {\"currentTab\": \"photo\"}}}",
                                "type": 3,
                                "url": "https://timg01.bdimg.com/timg?pano&size=f720_540&quality=80&sec=0&di=853892b12ca3c40f793c70a514a6ba5d&src=http%3A%2F%2Ftaojin-his.cdn.bcebos.com%2F574e9258d109b3de71057ccdc0bf6c81810a4cd9.jpg"
                            }],
                            "showtag": "[[\"\\u5e7f\\u544a\\u516c\\u53f8\"], [\"\"], \"\", 0, \"\"]"
                        }
                    }
                }
            },
            "src_name": "enterprise"
        },
        "ext_display": {
            "display_info": {
                "catalog_fields": null,
                "impression_tag": {
                    "hotel": "",
                    "life": ""
                },
                "redu": "0",
                "source_map": {
                    "shop_hours": {
                        "field_name": "webmining",
                        "priority": "0",
                        "uid": "2103382395956613259:webmining",
                        "update_time": "1583858047.2987"
                    }
                },
                "src_name": "display_info",
                "uids": ["2103382395956613259:redu", "9599476514331970728", "2103382395956613259:webmining"]
            }
        },
        "ext_type": 4,
        "f_flag": 2073,
        "father_son": 0,
        "geo": "1|12570863.78,3212928.62;12570863.78,3212928.62|12570863.78,3212928.62;",
        "geo_type": 2,
        "indoor_pano": "",
        "ismodified": 0,
        "name": "钰姣广告",
        "navi_update_time": 1593598861,
        "navi_x": "0",
        "navi_y": "0",
        "new_catalog_id": "140204",
        "pano": 1,
        "poiType": 0,
        "poi_click_num": 0,
        "poi_profile": 0,
        "primary_uid": "2103382395956613259",
        "prio_flag": 32,
        "route_flag": 0,
        "show_tag": [],
        "status": 1,
        "std_tag": "公司企业;公司",
        "std_tag_id": "2502",
        "storage_src": "api",
        "street_id": "b8277b46313bb375940319ad",
        "tag": "文化传媒 <font color=\"#c60a00\">广告</font>公司 公司企业",
        "ty": 2,
        "uid": "b8277b46313bb375940319ad",
        "view_type": 0,
        "x": 1257086378,
        "y": 321292862
    }, {
        "acc_flag": 0,
        "addr": "湖南省湘潭市雨湖区湘衡路182号附近",
        "address_norm": "[湖南省(430000)|PROV|1|][湘潭市(430300)|CITY|1|][雨湖区(430302)|AREA|1|][湘衡路()|ROAD|1|182号$]附近",
        "admin_info": {
            "area_id": 430302,
            "area_name": "雨湖区",
            "city_id": 430300,
            "city_name": "湘潭市"
        },
        "api_admin_info": {
            "area_code": 8155,
            "area_name": "雨湖区",
            "city_code": 313,
            "city_name": "湘潭市",
            "prov_code": 26,
            "prov_name": "湖南省"
        },
        "area": 8155,
        "area_name": "湘潭市雨湖区",
        "biz_type": 0,
        "brand_id": null,
        "catalogID": 0,
        "cla": [],
        "click_flag": 0,
        "detail": 1,
        "diPointX": 1256612909,
        "diPointY": 321050153,
        "di_tag": "传媒公司 公司企业 广告公司",
        "dis": -1,
        "dist2route": 0,
        "dist2start": 0,
        "ext": {
            "detail_info": {
                "areaid": "8155",
                "content_sug": {
                    "search_ext_data": {
                        "full_text": [{
                            "content": [
                                ["查看图片"],
                                ["#333333"]
                            ],
                            "jump_info": "baidumap://map/place/detail?popRoot=no&from=liebiao&show_type=detail_page&poi_ext_param=%7b%22anchor%22%3a%7b%22cardName%22%3a%22phototab%22%2c%22cardParams%22%3a%7b%22currentTab%22%3a%22photo%22%7d%7d%7d&uid=482b90b3f03314ba8405bf6f",
                            "label": [
                                ["图片"],
                                ["#F76545"], "#F76545", 4
                            ],
                            "priority": 6,
                            "type": 9
                        }]
                    },
                    "sug_ext_data": {
                        "full_text": [],
                        "sub_link_info": [{
                            "condition": [
                                [], 0, 0, 0, [0],
                                [0, 1],
                                ["", ""],
                                [0, 0]
                            ],
                            "content": [
                                ["查看图片"],
                                ["#333333"], 0, 0, 0, "", ""
                            ],
                            "jump_info": ["jumpto", "baidumap://map/place/detail?popRoot=no&from=liebiao&show_type=detail_page&poi_ext_param=%7b%22anchor%22%3a%7b%22cardName%22%3a%22phototab%22%2c%22cardParams%22%3a%7b%22currentTab%22%3a%22photo%22%7d%7d%7d&uid=482b90b3f03314ba8405bf6f"],
                            "label": [
                                ["图片"],
                                ["#F76545"], 0, 1, 4, "#F76545", ""
                            ],
                            "priority": 6,
                            "space": 2,
                            "type": 9
                        }]
                    }
                },
                "display_info_comment_label": {
                    "hotel": "",
                    "life": ""
                },
                "display_info_redu": "0",
                "from_pds": "1",
                "image": "https://taojin-his.cdn.bcebos.com/fc1f4134970a304ea2acb664ddc8a786c8175ca5.jpg",
                "link": [],
                "mbc": {
                    "markv": "3"
                },
                "name": "大众广告",
                "navi_xy": {
                    "bid": "222104437039586655",
                    "diPoint": {
                        "x": 12566129.09,
                        "y": 3210501.53
                    },
                    "navi_info": []
                },
                "overall_rating": "",
                "phone": "13203239808",
                "phone_risk": {
                    "bid": "222104437039586655",
                    "word": "如遇电话错误，可点击“报错”进行反馈"
                },
                "poi_address": "湖南省湘潭市雨湖区湘衡路182号附近",
                "point": {
                    "x": 12566129.09,
                    "y": 3210501.53
                },
                "price": "",
                "shop_hours_flag": "",
                "std_tag": "公司企业;公司",
                "tag": "广告公司",
                "validate": 0,
                "vs_content": {
                    "invisible": {
                        "bigdata": {
                            "photo_album": [{
                                "icon_url": "https://map-mobile-lbsapp.cdn.bcebos.com/tupian3x.png",
                                "jump_url": "baidumap://map/place/detail?popRoot=no&from=liebiao&uid=482b90b3f03314ba8405bf6f&show_type=detail_page&poi_ext_param={\"anchor\":{\"cardName\": \"phototab\", \"cardParams\": {\"currentTab\": \"photo\"}}}",
                                "type": 3,
                                "url": "https://timg01.bdimg.com/timg?pano&size=f720_540&quality=80&sec=0&di=4def78b12fc46fbe5e913bbfcf1b1fb8&src=http%3A%2F%2Ftaojin-his.cdn.bcebos.com%2Ffc1f4134970a304ea2acb664ddc8a786c8175ca5.jpg"
                            }, {
                                "icon_url": "https://map-mobile-lbsapp.cdn.bcebos.com/tupian3x.png",
                                "jump_url": "baidumap://map/place/detail?popRoot=no&from=liebiao&uid=482b90b3f03314ba8405bf6f&show_type=detail_page&poi_ext_param={\"anchor\":{\"cardName\": \"phototab\", \"cardParams\": {\"currentTab\": \"photo\"}}}",
                                "type": 3,
                                "url": "https://timg01.bdimg.com/timg?pano&size=f720_540&quality=80&sec=0&di=8d60b900690217baa4e248cdd841a036&src=http%3A%2F%2Ftaojin-his.cdn.bcebos.com%2Fd439b6003af33a87cf081e9bca5c10385243b5cd.jpg"
                            }, {
                                "icon_url": "https://map-mobile-lbsapp.cdn.bcebos.com/tupian3x.png",
                                "jump_url": "baidumap://map/place/detail?popRoot=no&from=liebiao&uid=482b90b3f03314ba8405bf6f&show_type=detail_page&poi_ext_param={\"anchor\":{\"cardName\": \"phototab\", \"cardParams\": {\"currentTab\": \"photo\"}}}",
                                "type": 3,
                                "url": "https://timg01.bdimg.com/timg?pano&size=f720_540&quality=80&sec=0&di=30063fae7c4267c0890feaab985b23ab&src=http%3A%2F%2Ftaojin-his.cdn.bcebos.com%2Fb812c8fcc3cec3fd7230a3ebda88d43f87942725.jpg"
                            }, {
                                "icon_url": "https://map-mobile-lbsapp.cdn.bcebos.com/tupian3x.png",
                                "jump_url": "baidumap://map/place/detail?popRoot=no&from=liebiao&uid=482b90b3f03314ba8405bf6f&show_type=detail_page&poi_ext_param={\"anchor\":{\"cardName\": \"phototab\", \"cardParams\": {\"currentTab\": \"photo\"}}}",
                                "type": 3,
                                "url": "https://timg01.bdimg.com/timg?pano&size=f720_540&quality=80&sec=0&di=9a44e8dd3ea4f00f534c4e90a8e89151&src=http%3A%2F%2Ftaojin-his.cdn.bcebos.com%2F8435e5dde71190efc55d6fdbc11b9d16fdfa6014.jpg"
                            }],
                            "showtag": "[[\"\\u5e7f\\u544a\\u516c\\u53f8\"], [\"\"], \"\", 0, \"\"]"
                        }
                    }
                }
            },
            "src_name": "enterprise"
        },
        "ext_display": {
            "display_info": {
                "catalog_fields": null,
                "impression_tag": {
                    "hotel": "",
                    "life": ""
                },
                "redu": "0",
                "source_map": [],
                "src_name": "display_info",
                "uids": ["222104437039586655:redu"]
            }
        },
        "ext_type": 4,
        "f_flag": 2057,
        "father_son": 0,
        "geo": "1|12566129.09,3210501.53;12566129.09,3210501.53|12566129.09,3210501.53;",
        "geo_type": 2,
        "name": "大众广告",
        "navi_update_time": 1591675263,
        "navi_x": "0",
        "navi_y": "0",
        "new_catalog_id": "140204",
        "poiType": 0,
        "poi_click_num": 0,
        "poi_profile": 0,
        "primary_uid": "222104437039586655",
        "prio_flag": 32,
        "route_flag": 0,
        "show_tag": [],
        "status": 1,
        "std_tag": "公司企业;公司",
        "std_tag_id": "2502",
        "storage_src": "api",
        "tag": "传媒公司 公司企业 <font color=\"#c60a00\">广告</font>公司",
        "tel": "13203239808",
        "ty": 2,
        "uid": "482b90b3f03314ba8405bf6f",
        "view_type": 0,
        "x": 1256612909,
        "y": 321050153
    }, {
        "acc_flag": 0,
        "addr": "湘潭市雨湖区开源路与江南大道交叉路口往东北约100米(九华.金水湾)",
        "address_norm": "[湖南省(430000)|PROV|0|][湘潭市(430300)|CITY|1|][雨湖区(430302)|AREA|1|][开源路()|ROAD|1|]与江南大道交叉路口往东北约100米(九华.金水湾)",
        "admin_info": {
            "area_id": 430302,
            "area_name": "雨湖区",
            "city_id": 430300,
            "city_name": "湘潭市"
        },
        "aoi": "软件学院",
        "api_admin_info": {
            "area_code": 8155,
            "area_name": "雨湖区",
            "city_code": 313,
            "city_name": "湘潭市",
            "prov_code": 26,
            "prov_name": "湖南省"
        },
        "area": 8155,
        "area_name": "湘潭市雨湖区",
        "biz_type": 0,
        "brand_id": null,
        "catalogID": 0,
        "cla": [],
        "click_flag": 0,
        "detail": 1,
        "diPointX": 1257202990,
        "diPointY": 321825735,
        "di_tag": "传媒公司 公司企业 广告公司",
        "dis": -1,
        "dist2route": 0,
        "dist2start": 0,
        "ext": {
            "detail_info": {
                "areaid": "8155",
                "content_sug": {
                    "search_ext_data": {
                        "full_text": []
                    },
                    "sug_ext_data": {
                        "full_text": [],
                        "sub_link_info": []
                    }
                },
                "from_pds": "1",
                "image": "https://taojin-his.cdn.bcebos.com/0ff41bd5ad6eddc4adac4c4637dbb6fd536633c0.jpg",
                "link": [],
                "mbc": {
                    "markv": "3"
                },
                "name": "森林广告",
                "overall_rating": "",
                "phone": "",
                "poi_address": "湘潭市雨湖区开源路与江南大道交叉路口往东北约100米(九华.金水湾)",
                "point": {
                    "x": 12572029.9,
                    "y": 3218257.35
                },
                "price": "",
                "shop_hours_flag": "",
                "std_tag": "公司企业;公司",
                "tag": "广告公司",
                "validate": 0,
                "vs_content": {
                    "invisible": {
                        "bigdata": {
                            "showtag": "[[\"\\u5e7f\\u544a\\u516c\\u53f8\"], [\"\"], \"\", 0, \"\"]"
                        }
                    }
                }
            },
            "src_name": "enterprise"
        },
        "ext_display": null,
        "ext_type": 4,
        "f_flag": 2057,
        "father_son": 0,
        "geo": "1|12572029.90,3218257.35;12572029.90,3218257.35|12572029.90,3218257.35;",
        "geo_type": 2,
        "name": "森林广告",
        "navi_update_time": 1591530394,
        "navi_x": "0",
        "navi_y": "0",
        "new_catalog_id": "140204",
        "poiType": 0,
        "poi_click_num": 0,
        "poi_profile": 0,
        "primary_uid": "1463965492542929491",
        "prio_flag": 32,
        "route_flag": 0,
        "show_tag": [],
        "status": 1,
        "std_tag": "公司企业;公司",
        "std_tag_id": "2502",
        "storage_src": "api",
        "tag": "传媒公司 公司企业 <font color=\"#c60a00\">广告</font>公司",
        "ty": 2,
        "uid": "fa6d00af2e5b3c7ba7c75674",
        "view_type": 0,
        "x": 1257202990,
        "y": 321825735
    }, {
        "acc_flag": 0,
        "addr": "湖南省湘潭市雨湖区迎宾东路86号",
        "address_norm": "[湖南省(430000)|PROV|1|][湘潭市(430300)|CITY|1|][雨湖区(430302)|AREA|1|][迎宾东路()|ROAD|1|86号$]",
        "admin_info": {
            "area_id": 430302,
            "area_name": "雨湖区",
            "city_id": 430300,
            "city_name": "湘潭市"
        },
        "aoi": "迎宾;白石广场",
        "api_admin_info": {
            "area_code": 8155,
            "area_name": "雨湖区",
            "city_code": 313,
            "city_name": "湘潭市",
            "prov_code": 26,
            "prov_name": "湖南省"
        },
        "area": 8155,
        "area_name": "湘潭市雨湖区",
        "biz_type": 0,
        "brand_id": null,
        "catalogID": 0,
        "cla": [],
        "click_flag": 0,
        "detail": 1,
        "diPointX": 1256841000,
        "diPointY": 321168900,
        "di_tag": "传媒公司 公司企业 广告公司",
        "dis": -1,
        "dist2route": 0,
        "dist2start": 0,
        "ext": {
            "detail_info": {
                "areaid": "8155",
                "content_sug": {
                    "search_ext_data": {
                        "full_text": []
                    },
                    "sug_ext_data": {
                        "full_text": [],
                        "sub_link_info": []
                    }
                },
                "display_info_comment_label": {
                    "hotel": "",
                    "life": ""
                },
                "display_info_redu": "0",
                "from_pds": "1",
                "image": "https://taojin-his.cdn.bcebos.com/dcc451da81cb39db54e6befedc160924ab183070.jpg",
                "link": [],
                "mbc": {
                    "markv": "3"
                },
                "name": "星辰广告",
                "navi_xy": {
                    "bid": "5543884654461163436",
                    "diPoint": {
                        "x": 12568420,
                        "y": 3211691
                    },
                    "navi_info": []
                },
                "overall_rating": "",
                "phone": "13257325903",
                "phone_risk": {
                    "bid": "5543884654461163436",
                    "word": "如遇电话错误，可点击“报错”进行反馈"
                },
                "poi_address": "湖南省湘潭市雨湖区迎宾东路86号",
                "point": {
                    "x": 12568410,
                    "y": 3211689
                },
                "price": "",
                "shop_hours_flag": "",
                "std_tag": "公司企业;公司",
                "tag": "广告公司",
                "validate": 0,
                "vs_content": {
                    "invisible": {
                        "bigdata": {
                            "photo_album": [{
                                "detail_url": "baidumap://map/component?target=street_scape_page&comName=streetscape&popRoot=no&param=%7B%22uid%22%3A%22bb363fa8363c728695f08cde%22%2C%22panotype%22%3A%22street%22%2C%22from_source%22%3A%22poidetail%22%7D",
                                "icon_url": "https://map-mobile-lbsapp.cdn.bcebos.com/quanjing3x.png",
                                "jump_url": "baidumap://map/place/detail?popRoot=no&from=liebiao&uid=bb363fa8363c728695f08cde&show_type=detail_page&poi_ext_param={\"anchor\":{\"cardName\": \"phototab\", \"cardParams\": {\"currentTab\": \"panorama\"}}}",
                                "type": 1,
                                "url": "https://mapsv0.bdimg.com/?qt=pr3dpoi&uid=bb363fa8363c728695f08cde&width=1024&height=456&watermark=&fovy=60&quality=80"
                            }, {
                                "icon_url": "https://map-mobile-lbsapp.cdn.bcebos.com/tupian3x.png",
                                "jump_url": "baidumap://map/place/detail?popRoot=no&from=liebiao&uid=bb363fa8363c728695f08cde&show_type=detail_page&poi_ext_param={\"anchor\":{\"cardName\": \"phototab\", \"cardParams\": {\"currentTab\": \"photo\"}}}",
                                "type": 3,
                                "url": "https://timg01.bdimg.com/timg?pano&size=f720_540&quality=80&sec=0&di=7b4c05e27a36e4fd22d827d8ebd815e1&src=http%3A%2F%2Ftaojin-his.cdn.bcebos.com%2Fdcc451da81cb39db54e6befedc160924ab183070.jpg"
                            }, {
                                "icon_url": "https://map-mobile-lbsapp.cdn.bcebos.com/tupian3x.png",
                                "jump_url": "baidumap://map/place/detail?popRoot=no&from=liebiao&uid=bb363fa8363c728695f08cde&show_type=detail_page&poi_ext_param={\"anchor\":{\"cardName\": \"phototab\", \"cardParams\": {\"currentTab\": \"photo\"}}}",
                                "type": 3,
                                "url": "https://timg01.bdimg.com/timg?pano&size=f720_540&quality=80&sec=0&di=127240a5801a67ef9278c9f5adb2e99c&src=http%3A%2F%2Ftaojin-his.cdn.bcebos.com%2Fd50735fae6cd7b8902893687002442a7d8330ec8.jpg"
                            }, {
                                "icon_url": "https://map-mobile-lbsapp.cdn.bcebos.com/tupian3x.png",
                                "jump_url": "baidumap://map/place/detail?popRoot=no&from=liebiao&uid=bb363fa8363c728695f08cde&show_type=detail_page&poi_ext_param={\"anchor\":{\"cardName\": \"phototab\", \"cardParams\": {\"currentTab\": \"photo\"}}}",
                                "type": 3,
                                "url": "https://timg01.bdimg.com/timg?pano&size=f720_540&quality=80&sec=0&di=6f03267569d4a8d4b2036e4de689267d&src=http%3A%2F%2Ftaojin-his.cdn.bcebos.com%2F1e30e924b899a9012bc0c68d13950a7b0308f590.jpg"
                            }],
                            "showtag": "[[\"\\u5e7f\\u544a\\u516c\\u53f8\"], [\"\"], \"\", 0, \"\"]"
                        }
                    }
                }
            },
            "src_name": "enterprise"
        },
        "ext_display": {
            "display_info": {
                "catalog_fields": null,
                "impression_tag": {
                    "hotel": "",
                    "life": ""
                },
                "redu": "0",
                "source_map": [],
                "src_name": "display_info",
                "uids": ["5543884654461163436:redu"]
            }
        },
        "ext_type": 4,
        "f_flag": 2057,
        "father_son": 0,
        "geo": "1|12568410.00,3211689.00;12568410.00,3211689.00|12568410.00,3211689.00;",
        "geo_type": 2,
        "indoor_pano": "",
        "ismodified": 1,
        "name": "星辰广告",
        "navi_update_time": 1590010064,
        "navi_x": "0",
        "navi_y": "0",
        "new_catalog_id": "140204",
        "pano": 1,
        "poiType": 0,
        "poi_click_num": 0,
        "poi_profile": 0,
        "primary_uid": "5543884654461163436",
        "prio_flag": 32,
        "route_flag": 0,
        "show_tag": [],
        "status": 1,
        "std_tag": "公司企业;公司",
        "std_tag_id": "2502",
        "storage_src": "api",
        "street_id": "bb363fa8363c728695f08cde",
        "tag": "传媒公司 公司企业 <font color=\"#c60a00\">广告</font>公司",
        "tel": "13257325903",
        "ty": 2,
        "uid": "bb363fa8363c728695f08cde",
        "view_type": 0,
        "x": 1256841000,
        "y": 321168900
    }, {
        "acc_flag": 0,
        "addr": "车站路556号",
        "address_norm": "[湖南省(26)|PROV|0|NONE][湘潭市(313)|CITY|0|NONE][雨湖区(8155)|AREA|0|NONE][车站路()|ROAD|1|NONE]556号",
        "area": 8155,
        "area_name": "湘潭市雨湖区",
        "biz_type": 0,
        "brand_id": null,
        "catalogID": 13,
        "cla": [
            [13, "餐饮"]
        ],
        "click_flag": 0,
        "detail": 1,
        "diPointX": 1257033411,
        "diPointY": 321394448,
        "di_tag": "创意菜 美食 餐馆",
        "dis": -1,
        "dist2route": 0,
        "dist2start": 0,
        "ext": {
            "detail_info": {
                "areaid": "1551",
                "business_scope": [{
                    "content": [{
                        "id": "7329448002352976521_f51567799ee8359eb034bddbd87f3981",
                        "name": "羊排",
                        "recommend_num": "2240"
                    }, {
                        "id": "7329448002352976521_7221ca72046af9de47164946dde37197",
                        "name": "小烧羊排",
                        "price": "45",
                        "recommend_num": "2240"
                    }, {
                        "id": "7329448002352976521_d09a735e1ff97841c9da40a6a9a0e4c3",
                        "name": "鱼香小豆腐",
                        "price": "38",
                        "recommend_num": "2227"
                    }, {
                        "id": "7329448002352976521_a0132ede89b64b7a764dfca45dce786a",
                        "name": "麻辣蔬菜煲",
                        "recommend_num": "2036"
                    }, {
                        "id": "7329448002352976521_36c789128192e4a638e69692b243c435",
                        "name": "鸡翅",
                        "recommend_num": "1932"
                    }, {
                        "id": "7329448002352976521_ed954d2b4109172c49be32e0494d63f4",
                        "name": "昔巷酸瓜干肠",
                        "price": "38",
                        "recommend_num": "1856"
                    }, {
                        "id": "7329448002352976521_5e45c911802a2d433c51d834316eb8f1",
                        "name": "秘制鸡翅",
                        "price": "40",
                        "recommend_num": "1663"
                    }, {
                        "id": "7329448002352976521_65071bba8fdfc98c13169628e6d1b651",
                        "name": "鱼汤",
                        "recommend_num": "1662"
                    }, {
                        "id": "7329448002352976521_fd4c555a230db00e75e0cc047dbf88bd",
                        "name": "虾片",
                        "recommend_num": "1592"
                    }, {
                        "id": "7329448002352976521_4c07e329a4d5332c1fdfbe63d5f593df",
                        "name": "樱桃鱼块",
                        "price": "38",
                        "recommend_num": "1474"
                    }, {
                        "id": "7329448002352976521_67146259ce5ad13565f97593d7216d00",
                        "name": "麦乳精",
                        "price": "16",
                        "recommend_num": "1451"
                    }, {
                        "id": "7329448002352976521_0fcd3e83cc70ff420959495f8ae74261",
                        "name": "口蘑鸡蛋",
                        "price": "39",
                        "recommend_num": "1432"
                    }, {
                        "id": "7329448002352976521_32d297a7fe9af599b4ef5145e1c8b6cb",
                        "name": "私家酸瓜干肠",
                        "recommend_num": "1385"
                    }, {
                        "id": "7329448002352976521_d3060357ee4fb75d76f6ec1c619faab5",
                        "name": "宫保虾球",
                        "price": "42",
                        "recommend_num": "1116"
                    }, {
                        "id": "7329448002352976521_c50ec414fe954aa3ab6e092c845e842f",
                        "name": "肉末茄子",
                        "price": "55",
                        "recommend_num": "1025"
                    }, {
                        "id": "7329448002352976521_2131e5c102c083ca9437484957f688e8",
                        "name": "北冰洋",
                        "price": "6",
                        "recommend_num": "986"
                    }, {
                        "id": "7329448002352976521_4bc778ac5335a81c73dba3e9fc942ebe",
                        "name": "咖喱鱼丸",
                        "recommend_num": "710"
                    }, {
                        "id": "7329448002352976521_c88be19857c356e17fbc2b524d47e70a",
                        "name": "杂粮饭",
                        "price": "3",
                        "recommend_num": "683"
                    }, {
                        "id": "7329448002352976521_763476725bf0e6659a169b69d4bc1d52",
                        "name": "豆腐",
                        "recommend_num": "575"
                    }, {
                        "id": "7329448002352976521_7df101a70c935bfb485441b7f7d91204",
                        "name": "水煮牛肉",
                        "price": "55",
                        "recommend_num": "140"
                    }, {
                        "id": "7329448002352976521_2a52a592ea80eef2e552c7cda9d4f5f7",
                        "name": "黑椒小豆腐",
                        "price": "26",
                        "recommend_num": "114"
                    }, {
                        "id": "7329448002352976521_aaacf0ab1714c7ff57a651d2aca92cb8",
                        "name": "肉末烧茄子",
                        "price": "28",
                        "recommend_num": "52"
                    }, {
                        "id": "7329448002352976521_4f13c20842b68d35d9d8e2e0232c269d",
                        "name": "烧茄子",
                        "recommend_num": "52"
                    }, {
                        "id": "7329448002352976521_ef7f9e7f09d680b52fb47757503c0604",
                        "name": "杏仁豆奶",
                        "recommend_num": "14"
                    }, {
                        "id": "7329448002352976521_b9adda8dd26ae04e63fe0940c744751f",
                        "name": "狮子头",
                        "recommend_num": "13"
                    }, {
                        "id": "7329448002352976521_99c5f6b00fe2334967b780399de2da7d",
                        "name": "茄子",
                        "recommend_num": "13"
                    }, {
                        "id": "7329448002352976521_221e9da3cfb226e2678dde9d73e9930a",
                        "name": "酸瓜干肠",
                        "recommend_num": "10"
                    }, {
                        "id": "7329448002352976521_c30cc538a616ec3c67978a5e9db8bd71",
                        "name": "藕丁",
                        "recommend_num": "9"
                    }, {
                        "id": "7329448002352976521_ff4a909b07a056eb52aec271c1888f3e",
                        "name": "酸辣小藕丁",
                        "recommend_num": "9"
                    }, {
                        "id": "7329448002352976521_d0584e22d2e2d6767944603239cc4b11",
                        "name": "昔巷酸瓜干",
                        "recommend_num": "6"
                    }, {
                        "id": "7329448002352976521_5fd90a1feb129ba9d6e2dab97f773ad9",
                        "name": "私家酸瓜干",
                        "recommend_num": "4"
                    }],
                    "type": "meishi"
                }],
                "business_service": [],
                "cater_tag": "位置好找 份量较小 环境不错 味道不错 服务很好",
                "cater_theme": [],
                "comment": [],
                "comment_num": 22,
                "description_flag": 1,
                "di_review_keyword": [],
                "from_pds": "1",
                "image": "http://S0.nuomi.bdimg.com/upload/2014/06-27/1403854542141-2646.jpg",
                "link": [],
                "mbc": {
                    "markv": 1
                },
                "name": "昔巷",
                "normal_features": {
                    "card": "1",
                    "parking": "1",
                    "room": "0",
                    "time_info": [],
                    "wifi": "1"
                },
                "overall_rating": "4.7",
                "phone": "",
                "poi_address": "车站路556号",
                "point": {
                    "x": 12570334.11,
                    "y": 4830744.08
                },
                "price": "50.0",
                "shop_hours": "12:00-15:00 18:00-22:00",
                "shop_hours_flag": 1,
                "status_label": "1",
                "std_tag": "美食;中餐厅",
                "tag": "中餐馆",
                "trade_tag": "位置好找 份量较小 环境不错 味道不错 服务很好",
                "validate": 1
            },
            "rich_info": {
                "recommend_commodity": [{
                    "commodity_name": "小烧羊排",
                    "image": [{
                        "imgUrl": "http://t11.baidu.com/it/u=1410278608,385061915&fm=22"
                    }],
                    "price": "45",
                    "recommend_num": "2240"
                }, {
                    "commodity_name": "鱼香小豆腐",
                    "image": [{
                        "imgUrl": "http://i3.s1.dpfile.com/pc/fa76a65fa1c9d28e3819aba6ecf2181d(700x700)/thumb.jpg"
                    }],
                    "price": "38",
                    "recommend_num": "2227"
                }, {
                    "commodity_name": "麻辣蔬菜煲",
                    "image": [{
                        "imgUrl": "http://t10.baidu.com/it/u=393219489,2349701892&fm=22"
                    }],
                    "price": null,
                    "recommend_num": "2036"
                }, {
                    "commodity_name": "昔巷酸瓜干肠",
                    "image": [{
                        "imgUrl": "http://t12.baidu.com/it/u=483305090,2490741815&fm=22"
                    }],
                    "price": "38",
                    "recommend_num": "1856"
                }]
            },
            "src_name": "cater"
        },
        "ext_display": null,
        "ext_type": 4,
        "f_flag": 258,
        "father_son": 0,
        "geo": "1|12570334.11,4830744.08;12570334.11,4830744.08|12570334.11,4830744.08;",
        "geo_type": 2,
        "indoor_pano": "",
        "ismodified": 0,
        "name": "昔巷",
        "navi_update_time": 1517466193,
        "navi_x": "12570334.11",
        "navi_y": "3213944.48",
        "new_catalog_id": "010000",
        "pano": 1,
        "poiType": 0,
        "poi_click_num": 0,
        "poi_profile": 0,
        "primary_uid": "7329448002352976521",
        "prio_flag": 0,
        "route_flag": 0,
        "show_tag": [],
        "status": 1,
        "std_tag": "美食;中餐厅",
        "std_tag_id": "1002",
        "storage_src": "api",
        "street_id": "634435ece8f3f55017c8f699",
        "tag": "",
        "ty": 2,
        "uid": "634435ece8f3f55017c8f699",
        "view_type": 0,
        "x": 1257033411,
        "y": 321394448
    }],
    "current_city": {
        "code": 313,
        "geo": "1|12573737.27,3208160.51;12573737.27,3208160.51|12573737.27,3208160.51;",
        "level": 13,
        "name": "湘潭市",
        "sup": 1,
        "sup_bus": 1,
        "sup_business_area": 0,
        "sup_lukuang": 0,
        "sup_subway": 0,
        "type": 2,
        "up_province_name": "湖南省"
    },
    "hot_city": ["北京市|131", "上海市|289", "广州市|257", "深圳市|340", "成都市|75", "天津市|332", "南京市|315", "杭州市|179", "武汉市|218"],
    "result": {
        "ad_display_type": 0,
        "aladdin_res_num": 135,
        "aladin_query_type": 0,
        "area_profile": 0,
        "bd_search_enable": 0,
        "broadcast_type": 0,
        "business_bound": "",
        "catalogID": 0,
        "cmd_no": 2,
        "count": 10,
        "current_null": 0,
        "data_security_filt_res": 0,
        "db": 0,
        "debug": 0,
        "illegal": 0,
        "jump_back": 1,
        "loc_attr": 1,
        "op_gel": 1,
        "page_num": 10,
        "pattern_sign": 0,
        "profile_uid": "2bfcb14cf5cb2cfcc23644f2",
        "qid": "9050548207628701427",
        "requery": "",
        "res_bound": "(12565539,3209338;12572619,3219420)",
        "res_bound_acc": "(0,0;0,0)",
        "res_l": 14,
        "res_x": "12569079.490000",
        "res_y": "3214379.430000",
        "result_show": 2,
        "return_query": "雨湖区广告",
        "rp_strategy": 0,
        "spec_dispnum": 0,
        "spothot": false,
        "sug_index": -1,
        "time": 0,
        "total": 149,
        "total_busline_num": 0,
        "tp": 0,
        "type": 36,
        "wd": "雨湖区广告",
        "wd2": "",
        "what": "广告",
        "where": "雨湖区",
        "uii_type": "china_main",
        "region": "0",
        "uii_qt": "poi",
        "login_debug": 0,
        "lbs_forward": {
            "param": [{
                "cloud_control_browser": "",
                "cloud_control_cf_tag": "",
                "cloud_control_params": "",
                "d_brand_id": "0",
                "d_query_attr_type": "4",
                "d_tag_info_list": "公司企业,广告公司",
                "divide_bound_areaid": 313,
                "divide_loc_areaid": 0,
                "divide_res_areaid": 313,
                "divide_type": 0,
                "is_viewcity_has_result": true,
                "query_show_click_flag": 0,
                "sample_experiment": [],
                "view_city": 313
            }]
        },
        "auth": "J3XIbPIzy2Va1QOPWe=FT35AcVBT3aN7uxHTEHBTBENtBnlQADZZzy1uVt1GgvPUDZYOYIZuBBto20N=5CGOF2gz4yBOxSrrlrIgHPWv3GuxVEtS@LyYxUvhgMZSguxzBEHLNRTVtcEWe1GD8zvOOuom=JL0fImDYLChjzgjyBKWHKEHBEQxuyWWJOLRIEjjg2J7M"
    },
    "damoce": null
}